src/zeroblanker.v
//ENGR 190 Lab 09 part 2, Blanker for hours if it displays 0
//Caleb Triplett 03/15/23
module zeroblanker #(parameter blanktoggle = 1)(
  input   [6:0] needblank, // unblanked value
  output  [6:0] blanked);  //blanked value
 assign blanked = (blanktoggle && (needblank[6:0] == 7'b1000000))
 ? 7'b1111111 : needblank;    
 //if the display is expressing 0, the display is blanked.
endmodule

src/hex7seg.v
// ENGR 190 Lab 7, 7 segment display from 4 bit hex
// Caleb Triplett, 02/22/23
module hex7seg (
  input  [3:0] c_i,      // 4-bit hexidecimal digit input
  output [6:0] disp_o);  // 7-bit output to a 7-segment display

  //     7-segment display segment # 6543210
  assign disp_o = (c_i == 4'h0) ? 7'b1000000 :
                  (c_i == 4'h1) ? 7'b1111001 :
                  (c_i == 4'h2) ? 7'b0100100 :
                  (c_i == 4'h3) ? 7'b0110000 :
                  (c_i == 4'h4) ? 7'b0011001 :
                  (c_i == 4'h5) ? 7'b0010010 :
                  (c_i == 4'h6) ? 7'b0000010 :
                  (c_i == 4'h7) ? 7'b1111000 :
                  (c_i == 4'h8) ? 7'b0000000 :
                  (c_i == 4'h9) ? 7'b0011000 :
                  (c_i == 4'hA) ? 7'b0001000 :
                  (c_i == 4'hb) ? 7'b0000011 :
                  (c_i == 4'hC) ? 7'b1000110 :
                  (c_i == 4'hd) ? 7'b0100001 :
                  (c_i == 4'hE) ? 7'b0000110 :
                                  7'b0001110;  //F
                  
endmodule

src/bcd2bin.v
//ENGR 190 Lab 09 part 2 bcd to binary converter
//Caleb Triplett 03/15/23
module bcd2bin(
input  [3:0] bcd_low,    
input  [3:0] bcd_high,    
output [6:0] bin_out);  
wire   [4:0] bcd0;  //most signifigant bcd
wire   [4:0] bcd1;  //least signifigant bcd
assign bcd0 = (bcd_high[3:0] > 4'b1001)? 4'b0000: bcd_high;  //if ms bit is > 9, be 0
assign bcd1 = (bcd_low[3:0] > 4'b1001)? 4'b0000: bcd_low;    //if ls bit is > 9, be 0
assign bin_out [6:0] = (bcd0 * 4'b1010  + bcd1);             //multiply the ms bit by 10 and add the ls bit

endmodule

src/bin2bcd.v
//ENGR 190 Lab 09 part 2, binary to bcd converter
//Caleb Triplett 03/15/23

module bin2bcd(
    input [6:0] bin_in,
    output [3:0] bcd_high_out,
    output [3:0] bcd_low_out
 );

 assign bcd_high_out = bin_in /10;
 assign bcd_low_out = bin_in % 10;

endmodule

src/hoursmanaged.v
//ENGR 190 Lab 09 part 2, manager to set hours to 12 when they reach 0
//Caleb Triplett 03/15/23

module hoursmanaged
#(parameter zeroed = 1, parameter hrmax= 11)(         
  input [6:0] binb4,
  output[6:0] bin_fresh);
  /*
 if zeroed is true and hrmax is set to 11, then when binb4 is equal 
 to 4 zeros (0000), bin_fresh will be set to 12 (11 + 1). 
 If binb4 is any other value, bin_fresh will be set to binb4.
 */ 
 assign bin_fresh = (zeroed && (binb4 == 4'b0000))? hrmax[6:0]+ 1: binb4;
endmodule

src/cntrStage.v
//ENGR 190 Lab 2 part 2 modified counterstage with active low sync load
//Caleb Triplett 03/15/23

module cntrStage
  #(parameter cntr_tc_p = 9) (  // counter terminal count
  input  clk_i,        // positive edge triggered clock
  input  [cntr_bits_p-1:0]nLoaded_i,    // synchronous active low load
  input  loadOrNah,
  input  enable_i,     // synchronous active high enable
  output term_cnt_o,   // set when at terminal count
  output [cntr_bits_p-1:0] count_o );  // count value

  // System task clog2 returns the ceiling of the log base 2 of the
  // argument.  Parameter cntr_bits_p is the minimum number of bits
  // needed to count 0 to cntr_tc_p.  It is not intended to be
  // overridden by higher level code, so is a localparam instead of
  // a parameter.
  localparam cntr_bits_p = $clog2(cntr_tc_p + 1);

  reg [cntr_bits_p-1:0] count_r = 0;    // count register

  always @(posedge clk_i) begin
    if (~loadOrNah) 
      count_r <= nLoaded_i;              //start loading if the active low load is 0 
    else if (enable_i) begin
      if (count_r == cntr_tc_p[cntr_bits_p-1:0])
        count_r <= 1'b0;            // enabled & at tc, wrap to 0
      else
        count_r <= count_r + 1'b1;  // enabled & not TC, so increment
    end
  end

  // set outputs from registers used in the always block
  assign count_o = count_r;
  assign term_cnt_o = (count_r == cntr_tc_p[cntr_bits_p-1:0]);

endmodule

src/clock2.v
//ENGR 190 Lab 09 part 2, 4 bit counter with active low load, toggleable zero blanker,
//toggleable hour manager, and a toggleable load from switch inputs
//Caleb Triplett 03/15/23
module clock2 #(parameter timey0 = 49999999, timey1 = 59, timey2 = 59, timey3 = 11, zeroz = 1) (
  input        clk_i,      
  input        nLoaded_i,   // active low synchronous load
  input        loadOrNah,   // load toggle
  input  [3:0] Lhourhigh,
  input  [3:0] Lhourlow,    // inputs with L in front of them are 
  input  [3:0] Lminhigh,    // loaded variables from switches
  input  [3:0] Lminlow,
  output  [6:0] Lhour,
  output  [6:0] Lmin,
  output [6:0] hrhighbcd,  // the outputs from the hex7seg
  output [6:0] hrlowbcd,
  output [6:0] minhighbcd,
  output [6:0] minlowbcd,
  output [6:0] sechighbcd,
  output [6:0] seclowbcd,
  output [6:0] seconds_o,  //outputs of each counter
  output [6:0] minutes_o,
  output [6:0] hours_o  
 );

 wire [6:0]  hex7needblank;//self explains
 wire [6:0] managedhour;  //the fixed hour to 12 when hours is displaying 0
 wire [3:0] sechigh;
 wire [3:0] seclow;
 wire [3:0] minlow;
 wire [3:0] minhigh;
 wire [3:0] hrlow;
 wire [3:0] hrhigh;
 wire stage3_en_w;
 and(tc0a1, stage1_en_w, stage2_en_w); //ands the second update counter 
                                       //and second terminal counts
 and(tc2a2, tc0a1, stage3_en_w);       //ands tc0a1 with the 
                                       //minutes terminal count
 wire tc2a2;
 wire tc0a1;

 wire stage1_en_w;
 wire stage2_en_w;
 assign Lmanagedhour = ((Lhour == timey3[6:0]+1) && zeroz) ? 7'd0 : Lhour; 
 /*
 you have to load the managed hour if the zeroed condition of 
 hourmanager is true and if the hours + 1 is equal to the loaded hour
 from the switches

 */

  cntrStage#(.cntr_tc_p (timey0))           
    stage0 (                    //how many times the seconds update counter
      .clk_i      (clk_i),
      .nLoaded_i  (4'b0000),
      .loadOrNah  (loadOrNah),
      .enable_i   (1'b1),       // always enabled
      .term_cnt_o (stage1_en_w),// stage stage 0 at TC (1-cycle pulse)
      .count_o    () );         // unused

  cntrStage#(.cntr_tc_p (timey1))           
    stage1 (                    //seconds counter
      .clk_i      (clk_i),      // same clock as stage 0
      .nLoaded_i  (4'b0000), 
      .loadOrNah  (loadOrNah),    
      .enable_i   (stage1_en_w),// only enabled when stage 0 is at TC
      .term_cnt_o (stage2_en_w),// stage stage 1 at TC (1-cycle pulse)         
      .count_o    (seconds_o) );

 cntrStage#(.cntr_tc_p (timey2))            
    stage2 (                    // minutes counter
      .clk_i      (clk_i),      // same clock as stage 0   
      .nLoaded_i  (Lmin),
      .loadOrNah  (loadOrNah),
      .enable_i   (tc0a1),      // only enabled when stage 1 is at TC 
                                // AND stage 0 is at TC
      .term_cnt_o (stage3_en_w),// stage stage 2 at TC (1-cycle pulse)
      .count_o    (minutes_o) );

 cntrStage#(.cntr_tc_p (timey3))      
    stage3 (                      // hours counter
      .clk_i      (clk_i),        // same clock as stage 0
      .nLoaded_i  (Lmanagedhour),
      .loadOrNah  (loadOrNah),      
      .enable_i   (tc2a2),        // only enabled when stage 2 is at TC AND
                                  // stage 1 is at TC AND stage 0 is at TC
      .term_cnt_o (),             // unused
      .count_o    (hours_o) );
 hoursmanaged#(
  .zeroed  (zeroz),               //zeroed is toggleable
  .hrmax   (timey3))              
  mangerH (
  .binb4  (hours_o),
  .bin_fresh (managedhour) );    //when time 0, be 12
 

 bin2bcd sec(
  .bin_in(seconds_o),
  .bcd_high_out(sechigh),
  .bcd_low_out(seclow));
  
 bin2bcd mins(
  .bin_in(minutes_o),
  .bcd_high_out(minhigh),
  .bcd_low_out(minlow) );
 
 bin2bcd hr(
  .bin_in(managedhour),          //translates info from managedhour to 
                                 //the hex7seg
  .bcd_high_out(hrhigh),
  .bcd_low_out(hrlow));
 
 bcd2bin Hbcd(                       
  .bcd_high         (Lhourhigh),  //leftmost 4 switches
  .bcd_low          (Lhourlow),   //next 4 switches
  .bin_out          (Lhour));
 bcd2bin Mbcd(
  .bcd_high         (Lminhigh),   //next 4 switches
  .bcd_low          (Lminlow),    // next 4 switches
  .bin_out          (Lmin));

hex7seg segs1 (
 .disp_o(hex7needblank),         //sends output of ms hours output to 
                                 //zeroblanker
 .c_i(hrhigh)
 );
hex7seg segs2 (
 .disp_o(hrlowbcd),
 .c_i(hrlow)
 );
 hex7seg segs3 (
 .disp_o(minhighbcd),
 .c_i(minhigh)
 );
 hex7seg segs4 (
 .disp_o(minlowbcd),
 .c_i(minlow)
 );
 hex7seg seg5 (
 .disp_o(sechighbcd),
 .c_i(sechigh)
 );
 hex7seg segs6 (
 .disp_o(seclowbcd),
 .c_i(seclow)
 );
 
 zeroblanker#(.blanktoggle  (1'b1)) zerah(
  .needblank  (hex7needblank),
  .blanked    (hrhighbcd)    //makes the display blanked instead of 
                             //express 0 on the hours 
 );
    



endmodule

sim/clock2_tb.v
//ENGR 190 Lab 2 part 2, Testbench for clock2 module
//Caleb Triplett 03/15/23
`timescale 1s/10ms 

module clock2_tb;
reg            clk_r = 1;
reg     [15:0] loading_r = 16'h1259; 
reg            loadOrNah_r = 1;
wire [6:0]hourhigh;
wire [6:0]hourlow;
wire [6:0]minhigh;
wire [6:0]minlow;
wire [6:0]sechigh;
wire [6:0]seclow;
always
    #0.250 clk_r = ~clk_r;    //2 cycles will happen per second
initial begin
$dumpfile("a.vcd");
$dumpvars;
$display("Time Clock hrhigh   hrLow   minhigh  minlow  sechigh   seclow");
$monitor("%4d  %1b     %3h    %3h    %3h     %3h    %3h     %3h", 
$time, clk_r, hourhigh, hourlow, minhigh, minlow, sechigh, seclow);
#0.25 loadOrNah_r = 0;   //@t=.25  
#1    loadOrNah_r = 1;   //@t=1.25 
#4.25 $finish;             //@t=5.50
end 
 clock2 #(.timey0 (1'b1),
         .timey1   (1'b1)
        
        ) 
  DUT(  
  .Lhourhigh  (loading_r [15:12]),
  .Lhourlow  (loading_r [11:8 ]),
  .Lminhigh  (loading_r [ 7:4 ]),
  .Lminlow (loading_r [ 3:0 ]),
  .clk_i            (clk_r),
  .loadOrNah     (loadOrNah_r),  
  .hrhighbcd (hourhigh),
  .hrlowbcd  (hourlow),
  .minhighbcd(minhigh),
  .minlowbcd (minlow),
  .sechighbcd(sechigh),
  .seclowbcd (seclow));
endmodule

sim/a.vcd
$date
	Sat Mar 18 22:29:32 2023
$end
$version
	Icarus Verilog
$end
$timescale
	10ms
$end
$scope module clock2_tb $end
$var wire 7 ! seclow [6:0] $end
$var wire 7 " sechigh [6:0] $end
$var wire 7 # minlow [6:0] $end
$var wire 7 $ minhigh [6:0] $end
$var wire 7 % hourlow [6:0] $end
$var wire 7 & hourhigh [6:0] $end
$var reg 1 ' clk_r $end
$var reg 1 ( loadOrNah_r $end
$var reg 16 ) loading_r [15:0] $end
$scope module DUT $end
$var wire 4 * Lhourhigh [3:0] $end
$var wire 4 + Lhourlow [3:0] $end
$var wire 4 , Lminhigh [3:0] $end
$var wire 4 - Lminlow [3:0] $end
$var wire 1 ' clk_i $end
$var wire 1 ( loadOrNah $end
$var wire 1 . nLoaded_i $end
$var wire 1 / tc0a1 $end
$var wire 1 0 tc2a2 $end
$var wire 1 1 stage3_en_w $end
$var wire 1 2 stage2_en_w $end
$var wire 1 3 stage1_en_w $end
$var wire 7 4 seconds_o [6:0] $end
$var wire 7 5 seclowbcd [6:0] $end
$var wire 4 6 seclow [3:0] $end
$var wire 7 7 sechighbcd [6:0] $end
$var wire 4 8 sechigh [3:0] $end
$var wire 7 9 minutes_o [6:0] $end
$var wire 7 : minlowbcd [6:0] $end
$var wire 4 ; minlow [3:0] $end
$var wire 7 < minhighbcd [6:0] $end
$var wire 4 = minhigh [3:0] $end
$var wire 7 > managedhour [6:0] $end
$var wire 7 ? hrlowbcd [6:0] $end
$var wire 4 @ hrlow [3:0] $end
$var wire 7 A hrhighbcd [6:0] $end
$var wire 4 B hrhigh [3:0] $end
$var wire 7 C hours_o [6:0] $end
$var wire 7 D hex7needblank [6:0] $end
$var wire 7 E Lmin [6:0] $end
$var wire 1 F Lmanagedhour $end
$var wire 7 G Lhour [6:0] $end
$var parameter 1 H timey0 $end
$var parameter 1 I timey1 $end
$var parameter 32 J timey2 $end
$var parameter 32 K timey3 $end
$var parameter 32 L zeroz $end
$scope module Hbcd $end
$var wire 4 M bcd_high [3:0] $end
$var wire 4 N bcd_low [3:0] $end
$var wire 7 O bin_out [6:0] $end
$var wire 5 P bcd1 [4:0] $end
$var wire 5 Q bcd0 [4:0] $end
$upscope $end
$scope module Mbcd $end
$var wire 4 R bcd_high [3:0] $end
$var wire 4 S bcd_low [3:0] $end
$var wire 7 T bin_out [6:0] $end
$var wire 5 U bcd1 [4:0] $end
$var wire 5 V bcd0 [4:0] $end
$upscope $end
$scope module hr $end
$var wire 7 W bin_in [6:0] $end
$var wire 4 X bcd_low_out [3:0] $end
$var wire 4 Y bcd_high_out [3:0] $end
$upscope $end
$scope module mangerH $end
$var wire 7 Z binb4 [6:0] $end
$var wire 7 [ bin_fresh [6:0] $end
$var parameter 32 \ hrmax $end
$var parameter 32 ] zeroed $end
$upscope $end
$scope module mins $end
$var wire 7 ^ bin_in [6:0] $end
$var wire 4 _ bcd_low_out [3:0] $end
$var wire 4 ` bcd_high_out [3:0] $end
$upscope $end
$scope module sec $end
$var wire 7 a bin_in [6:0] $end
$var wire 4 b bcd_low_out [3:0] $end
$var wire 4 c bcd_high_out [3:0] $end
$upscope $end
$scope module seg5 $end
$var wire 4 d c_i [3:0] $end
$var wire 7 e disp_o [6:0] $end
$upscope $end
$scope module segs1 $end
$var wire 4 f c_i [3:0] $end
$var wire 7 g disp_o [6:0] $end
$upscope $end
$scope module segs2 $end
$var wire 4 h c_i [3:0] $end
$var wire 7 i disp_o [6:0] $end
$upscope $end
$scope module segs3 $end
$var wire 4 j c_i [3:0] $end
$var wire 7 k disp_o [6:0] $end
$upscope $end
$scope module segs4 $end
$var wire 4 l c_i [3:0] $end
$var wire 7 m disp_o [6:0] $end
$upscope $end
$scope module segs6 $end
$var wire 4 n c_i [3:0] $end
$var wire 7 o disp_o [6:0] $end
$upscope $end
$scope module stage0 $end
$var wire 1 ' clk_i $end
$var wire 1 p count_o $end
$var wire 1 q enable_i $end
$var wire 1 ( loadOrNah $end
$var wire 1 r nLoaded_i $end
$var wire 1 3 term_cnt_o $end
$var parameter 32 s cntr_bits_p $end
$var parameter 1 t cntr_tc_p $end
$var reg 1 u count_r $end
$upscope $end
$scope module stage1 $end
$var wire 1 ' clk_i $end
$var wire 1 v count_o $end
$var wire 1 3 enable_i $end
$var wire 1 ( loadOrNah $end
$var wire 1 w nLoaded_i $end
$var wire 1 2 term_cnt_o $end
$var parameter 32 x cntr_bits_p $end
$var parameter 1 y cntr_tc_p $end
$var reg 1 z count_r $end
$upscope $end
$scope module stage2 $end
$var wire 1 ' clk_i $end
$var wire 6 { count_o [5:0] $end
$var wire 1 / enable_i $end
$var wire 1 ( loadOrNah $end
$var wire 6 | nLoaded_i [5:0] $end
$var wire 1 1 term_cnt_o $end
$var parameter 32 } cntr_bits_p $end
$var parameter 32 ~ cntr_tc_p $end
$var reg 6 !" count_r [5:0] $end
$upscope $end
$scope module stage3 $end
$var wire 1 ' clk_i $end
$var wire 4 "" count_o [3:0] $end
$var wire 1 0 enable_i $end
$var wire 1 ( loadOrNah $end
$var wire 4 #" nLoaded_i [3:0] $end
$var wire 1 $" term_cnt_o $end
$var parameter 32 %" cntr_bits_p $end
$var parameter 32 &" cntr_tc_p $end
$var reg 4 '" count_r [3:0] $end
$upscope $end
$scope module zerah $end
$var wire 7 (" needblank [6:0] $end
$var wire 7 )" blanked [6:0] $end
$var parameter 1 *" blanktoggle $end
$upscope $end
$upscope $end
$upscope $end
$enddefinitions $end
$comment Show the parameter values. $end
$dumpall
1*"
b1011 &"
b100 %"
b111011 ~
b110 }
1y
b1 x
1t
b1 s
b1 ]
b1011 \
b1 L
b1011 K
b111011 J
1I
1H
$end
#0
$dumpvars
b1111001 )"
b1111001 ("
b0 '"
0$"
b0 #"
b0 ""
b0 !"
b111011 |
b0 {
0z
0w
0v
1u
0r
1q
1p
b1000000 o
b0 n
b1000000 m
b0 l
b1000000 k
b0 j
b100100 i
b10 h
b1111001 g
b1 f
b1000000 e
b0 d
b0 c
b0 b
b0 a
b0 `
b0 _
b0 ^
b1100 [
b0 Z
b1 Y
b10 X
b1100 W
b101 V
b1001 U
b111011 T
b1001 S
b101 R
b1 Q
b10 P
b1100 O
b10 N
b1 M
b1100 G
0F
b111011 E
b1111001 D
b0 C
b1 B
b1111001 A
b10 @
b100100 ?
b1100 >
b0 =
b1000000 <
b0 ;
b1000000 :
b0 9
b0 8
b1000000 7
b0 6
b1000000 5
b0 4
13
02
01
00
0/
z.
b1001 -
b101 ,
b10 +
b1 *
b1001001011001 )
1(
1'
b1111001 &
b100100 %
b1000000 $
b1000000 #
b1000000 "
b1000000 !
$end
#25
0(
0'
#50
b10010 $
b10010 <
b10010 k
b11000 #
b11000 :
b11000 m
b101 =
b101 `
b101 j
b1001 ;
b1001 _
b1001 l
03
11
b111011 9
b111011 ^
b111011 {
b111011 !"
0p
0u
1'
#75
0'
#100
1'
#125
0'
1(
#150
13
1p
1u
1'
#175
0'
#200
b1111001 !
b1111001 5
b1111001 o
03
12
b1 6
b1 b
b1 n
0p
0u
b1 4
b1 a
1v
1z
1'
#225
0'
#250
10
1/
13
1p
1u
1'
#275
0'
#300
b1111001 %
b1111001 ?
b1111001 i
b1111111 &
b1111111 A
b1111111 )"
b1000000 D
b1000000 g
b1000000 ("
b1 @
b1 X
b1 h
b0 B
b0 Y
b0 f
0/
b1000000 !
b1000000 5
b1000000 o
b1000000 $
b1000000 <
b1000000 k
b1000000 #
b1000000 :
b1000000 m
b1 >
b1 W
b1 [
03
02
b0 6
b0 b
b0 n
00
b0 =
b0 `
b0 j
b0 ;
b0 _
b0 l
0p
0u
b0 4
b0 a
0v
0z
01
b0 9
b0 ^
b0 {
b0 !"
b1 C
b1 Z
b1 ""
b1 '"
1'
#325
0'
#350
13
1p
1u
1'
#375
0'
#400
b1111001 !
b1111001 5
b1111001 o
03
12
b1 6
b1 b
b1 n
0p
0u
b1 4
b1 a
1v
1z
1'
#425
0'
#450
1/
13
1p
1u
1'
#475
0'
#500
0/
b1000000 !
b1000000 5
b1000000 o
b1111001 #
b1111001 :
b1111001 m
03
02
b0 6
b0 b
b0 n
b1 ;
b1 _
b1 l
0p
0u
b0 4
b0 a
0v
0z
b1 9
b1 ^
b1 {
b1 !"
1'
#525
0'
#550
13
1p
1u
1'
